alpha_dom/__init__.py
alpha_dom/__main__.py
alpha_dom/cards/__init__.py
alpha_dom/cards/expansions/Base/Artisan.json
alpha_dom/cards/expansions/Base/Bandit.json
alpha_dom/cards/expansions/Base/Bureaucrat.json
alpha_dom/cards/expansions/Base/Cellar.json
alpha_dom/cards/expansions/Base/Chapel.json
alpha_dom/cards/expansions/Base/Council Room.json
alpha_dom/cards/expansions/Base/Festival.json
alpha_dom/cards/expansions/Base/Gardens.json
alpha_dom/cards/expansions/Base/Harbinger.json
alpha_dom/cards/expansions/Base/Library.json
alpha_dom/cards/expansions/Base/Market.json
alpha_dom/cards/expansions/Base/Merchant.json
alpha_dom/cards/expansions/Base/Militia.json
alpha_dom/cards/expansions/Base/Mine.json
alpha_dom/cards/expansions/Base/Moat.json
alpha_dom/cards/expansions/Base/Moneylender.json
alpha_dom/cards/expansions/Base/Poacher.json
alpha_dom/cards/expansions/Base/Remodel.json
alpha_dom/cards/expansions/Base/Sentry.json
alpha_dom/cards/expansions/Base/Smithy.json
alpha_dom/cards/expansions/Base/Throne Room.json
alpha_dom/cards/expansions/Base/Vassal.json
alpha_dom/cards/expansions/Base/Village.json
alpha_dom/cards/expansions/Base/Witch.json
alpha_dom/cards/expansions/Base/Workshop.json
alpha_dom/cards/expansions/Common/Copper.json
alpha_dom/cards/expansions/Common/Curse.json
alpha_dom/cards/expansions/Common/Duchy.json
alpha_dom/cards/expansions/Common/Estate.json
alpha_dom/cards/expansions/Common/Gold.json
alpha_dom/cards/expansions/Common/Province.json
alpha_dom/cards/expansions/Common/Silver.json
alpha_dom/cards/model.py
alpha_dom-0.1.4.dist-info/LICENSE
alpha_dom-0.1.4.dist-info/METADATA
alpha_dom-0.1.4.dist-info/WHEEL
alpha_dom-0.1.4.dist-info/RECORD
