Metadata-Version: 2.1
Name: alpha-dom
Version: 0.1.4
Summary: Playing Dominion with Deep Reinforcement Learning
License: MIT
Author: Najib Ishaq
Author-email: najib_ishaq@zoho.com
Requires-Python: >=3.11,<4.0
Classifier: License :: OSI Approved :: MIT License
Classifier: Programming Language :: Python :: 3
Classifier: Programming Language :: Python :: 3.11
Requires-Dist: pydantic (>=1.10.9,<2.0.0)
